README.rst
setup.py
engineio_client/__init__.py
engineio_client/client.py
engineio_client/emitter.py
engineio_client/parser.py
engineio_client/transport.py
engineio_client/utils.py
engineio_client/transports/__init__.py
engineio_client/transports/polling.py
python_engineio_client.egg-info/PKG-INFO
python_engineio_client.egg-info/SOURCES.txt
python_engineio_client.egg-info/dependency_links.txt
python_engineio_client.egg-info/not-zip-safe
python_engineio_client.egg-info/requires.txt
python_engineio_client.egg-info/top_level.txt